accurating/__init__.py
accurating/model.py
accurating/tests/__init__.py
accurating/tests/model_test.py
accurating-0.7.0.dist-info/LICENSE
accurating-0.7.0.dist-info/METADATA
accurating-0.7.0.dist-info/WHEEL
accurating-0.7.0.dist-info/RECORD
