Metadata-Version: 2.3
Name: AccuRating
Version: 0.7.0
Summary: AccuRating is a library for accurate player ranking based on match results.
Author: Lukasz Lew
Author-email: lukasz.lew@gmail.com
Requires-Python: >=3.10,<4.0
Classifier: Programming Language :: Python :: 3
Classifier: Programming Language :: Python :: 3.10
Classifier: Programming Language :: Python :: 3.11
Classifier: Programming Language :: Python :: 3.12
Classifier: Programming Language :: Python :: 3.13
Requires-Dist: jax (>=0.4.8,<0.5.0)
Requires-Dist: jaxlib (>=0.4.7,<0.5.0)
Requires-Dist: requests (>=2.32.3,<3.0.0)
Requires-Dist: tabulate (>=0.9.0,<0.10.0)
Requires-Dist: types-requests (>=2.30.0.0,<3.0.0.0)
Requires-Dist: types-tabulate (>=0.9.0.2,<0.10.0.0)
Project-URL: Documentation, https://lukaszlew.github.io/accurating/
Project-URL: Homepage, https://github.com/lukaszlew/accurating
